{
  "specs": {},
  "functional_spec_count": {},
  "testsuites": [
    {
      "cases": [
        {
          "classname": "Guvi.tests.test_login",
          "name": "test_Excel",
          "developer": "-",
          "test_description": "",
          "status": "Failed",
          "logs": "<ul style='list-style-type: none; padding: 0;'></ul>",
          "details": "Message: TypeError: cannot unpack non-iterable NoneType object\nDetails: self = <tests.test_login.TestLogin object at 0x0000027BF4D5B130>, setup = None\n\n    def test_Excel(self, setup):\n>       driver, wait = setup\n        ^^^^^^^^^^^^\nE       TypeError: cannot unpack non-iterable NoneType object\n\nGuvi\\tests\\test_login.py:69: TypeError",
          "functional_specifications": [],
          "categories": []
        }
      ]
    }
  ],
  "test_environment": "Development",
  "timestamp": "15 Apr 2026, 18:31",
  "img_url": "https://icon.icepanel.io/Technology/svg/pytest.svg",
  "test_status": "complete",
  "report_title": "pytest HTML Report",
  "category_count": {},
  "all_categories": []
}